cpquant/.env
cpquant/__init__.py
cpquant/cpquant.py
cpquant/data.py
cpquant/stats.py
cpquant/trade.py
cpquant-0.1.8.dist-info/LICENSE
cpquant-0.1.8.dist-info/METADATA
cpquant-0.1.8.dist-info/WHEEL
cpquant-0.1.8.dist-info/RECORD
